[
    {
        "mailbox": "tv0hu@tender7.com----fGxPHRb66RjGH5",
        "account": "tv0hu@tender7.com",
        "password": "fGxPHRb66RjGH5",
        "1step_number": "4160210835023154",
        "1step_month": "12",
        "1step_year": "2026",
        "1step_code": "210",
        "2step_number": "3584030116427522",
        "2step_year": "20",
        "2step_month": "2706",
        "2step_code": "828",
        "real_name": "admno",
        "street": "Nuwara Eliya - Badulla R, 124/1",
        "city": "Nuwara Eliya",
        "state": "NuwaraEliya",
        "postcode": "52",
        "country_full_name": "Sri Lanka",
        "country_code": "LK",
        "phone_number_id": "3810843142",
        "phone_number": "787574226",
        "phone_number_url": "https://api.small5.co/hub/en/proxy.php?action=getStatus&id=3810843142&platform=sms",
        "numeric_id": 64,
        "dialing_code": "94"
    }
]